kadaptest4/__init__.py
kadaptest4/data.py
kadaptest4/vin_decoder_api/__init__.py
kadaptest4/vin_decoder_api/decoder.py
kadaptest4-0.0.1.dist-info/LICENSE
kadaptest4-0.0.1.dist-info/METADATA
kadaptest4-0.0.1.dist-info/WHEEL
kadaptest4-0.0.1.dist-info/top_level.txt
kadaptest4-0.0.1.dist-info/RECORD
